erdcIO/__init__.py
erdcIO/base.py
erdcIO/cshoreio.py
erdcIO/prepDataLib.py
erdcIO/swashio.py
erdcIO/writeRunRead.py
erdcIO/ww3io.py
erdcIO/testbedutils/__init__.py
erdcIO/testbedutils/dirtLib.py
erdcIO/testbedutils/geoprocess.py
erdcIO/testbedutils/sblib.py
erdcIO/testbedutils/waveLib.py
erdcIO/writeRunRead/__init__.py
erdcIO-0.1.14.dist-info/METADATA
erdcIO-0.1.14.dist-info/WHEEL
erdcIO-0.1.14.dist-info/top_level.txt
erdcIO-0.1.14.dist-info/RECORD
