Metadata-Version: 2.1
Name: erdcIO
Version: 0.1.14
Summary: Coastal Model Test Bed WriteRunRead for ERDC Numerical Models
Home-page: UNKNOWN
Author: Spicer Bak and Ty Hesser
Author-email: thesser1@gmail.com
License: UNKNOWN
Platform: UNKNOWN
Requires-Dist: numpy
Requires-Dist: datetime
Requires-Dist: testbedutils
Requires-Dist: getdatatestbed
Requires-Dist: netCDF4
Requires-Dist: f90nml
